{
  "_id": "sdTjTdmBYkJ4Ak97",
  "name": "Lucky Parrot",
  "type": "feature",
  "img": "systems/pirateborg/tokens/lucky-parrot.png",
  "effects": [
    {
      "_id": "pbEffParrotAgi1",
      "name": "Lucky Parrot - Agility Bonus",
      "icon": "systems/pirateborg/tokens/lucky-parrot.png",
      "changes": [
        {
          "key": "system.abilities.agility.value",
          "mode": 2,
          "value": 1
        }
      ],
      "disabled": false,
      "transfer": false,
      "flags": {},
      "_key": "!items.effects!sdTjTdmBYkJ4Ak97.pbEffParrotAgi1"
    },
    {
      "_id": "pbEffParrotPre1",
      "name": "Lucky Parrot - Presence Bonus",
      "icon": "systems/pirateborg/tokens/lucky-parrot.png",
      "changes": [
        {
          "key": "system.abilities.presence.value",
          "mode": 2,
          "value": 2
        }
      ],
      "disabled": false,
      "transfer": false,
      "flags": {},
      "_key": "!items.effects!sdTjTdmBYkJ4Ak97.pbEffParrotPre1"
    }
  ],
  "folder": null,
  "sort": 0,
  "flags": {},
  "ownership": {
    "default": 0
  },
  "_stats": {
    "coreVersion": "12.331",
    "systemId": null,
    "systemVersion": null,
    "createdTime": null,
    "modifiedTime": null,
    "lastModifiedBy": null,
    "duplicateSource": null
  },
  "system": {
    "description": "<p>A colorful, talking, flying bird. Roll d6 for Devil&rsquo;s Luck points each day.</p>\n<p>Agility: +1.</p>\n<p>Presence: +2.</p>\n<p>HP: d2+toughness.</p>\n<p>Beak Peck: d4</p>",
    "featureType": "Class",
    "maxQuantity": 1,
    "quantity": 1,
    "actionMacro": "",
    "actionMacroLabel": "",
    "startingBonusItems": "pirateborg.class-tall-tale;Lucky Parrot - Beak Peck",
    "startingBonusRolls": "",
    "flavorText": ""
  },
  "_key": "!items!sdTjTdmBYkJ4Ak97"
}
